{
    "version": "https://jsonfeed.org/version/1",
    "title": "MAXshiro • All posts by \"awvs\" tag",
    "description": "Discover and Record the world.",
    "home_page_url": "http://maxshiroi.top",
    "items": [
        {
            "id": "http://maxshiroi.top/linux/docker/203008/",
            "url": "http://maxshiroi.top/linux/docker/203008/",
            "title": "在docker中设置并安装AWVS和Nessus漏扫程序",
            "date_published": "2023-06-12T12:30:08.000Z",
            "content_html": "<p><a href=\"https://blog.csdn.net/WJ_11_13/article/details/127426899\">https://blog.csdn.net/WJ_11_13/article/details/127426899</a><br>\n<a href=\"https://hub.docker.com/r/secfa/docker-awvs\">https://hub.docker.com/r/secfa/docker-awvs</a></p>\n",
            "tags": [
                "linux",
                "docker",
                "nessus",
                "awvs"
            ]
        }
    ]
}